
{
  "placeholderImages": [
    {
      "id": "hero-main",
      "description": "Halal Partner mobile app interface showcase",
      "imageUrl": "https://6000-firebase-studio-1781788993237.cluster-j6d3cbsvdbe5uxnhqrfzzeyj7i.cloudworkstations.dev/capra/attachedImages/779f8c95-42ec-4c45-8508-17c25112b818/image_3212c471-dd6c-43ce-bf7c-21f20fdde6d8.png",
      "imageHint": "mobile app"
    },
    {
      "id": "portfolio-1",
      "description": "SaaS Dashboard UI",
      "imageUrl": "https://picsum.photos/seed/dashboard/800/600",
      "imageHint": "saas dashboard"
    },
    {
      "id": "portfolio-2",
      "description": "Mobile App Interface",
      "imageUrl": "https://picsum.photos/seed/mobile/800/600",
      "imageHint": "mobile app interface"
    },
    {
      "id": "portfolio-3",
      "description": "E-commerce Web Platform",
      "imageUrl": "https://picsum.photos/seed/ecommerce/800/600",
      "imageHint": "ecommerce website"
    },
    {
      "id": "about-team",
      "description": "Prospira collaborative workspace",
      "imageUrl": "https://picsum.photos/seed/team/1200/600",
      "imageHint": "agency team"
    }
  ]
}
